redpanda_connect/__init__.py
redpanda_connect/_convert.py
redpanda_connect/_grpc.py
redpanda_connect/core.py
redpanda_connect/errors.py
redpanda_connect/py.typed
redpanda_connect/_proto/redpanda/runtime/v1alpha1/agent_pb2.py
redpanda_connect/_proto/redpanda/runtime/v1alpha1/agent_pb2.pyi
redpanda_connect/_proto/redpanda/runtime/v1alpha1/agent_pb2_grpc.py
redpanda_connect/_proto/redpanda/runtime/v1alpha1/agent_pb2_grpc.pyi
redpanda_connect/_proto/redpanda/runtime/v1alpha1/input_pb2.py
redpanda_connect/_proto/redpanda/runtime/v1alpha1/input_pb2.pyi
redpanda_connect/_proto/redpanda/runtime/v1alpha1/input_pb2_grpc.py
redpanda_connect/_proto/redpanda/runtime/v1alpha1/input_pb2_grpc.pyi
redpanda_connect/_proto/redpanda/runtime/v1alpha1/message_pb2.py
redpanda_connect/_proto/redpanda/runtime/v1alpha1/message_pb2.pyi
redpanda_connect/_proto/redpanda/runtime/v1alpha1/message_pb2_grpc.py
redpanda_connect/_proto/redpanda/runtime/v1alpha1/message_pb2_grpc.pyi
redpanda_connect/_proto/redpanda/runtime/v1alpha1/output_pb2.py
redpanda_connect/_proto/redpanda/runtime/v1alpha1/output_pb2.pyi
redpanda_connect/_proto/redpanda/runtime/v1alpha1/output_pb2_grpc.py
redpanda_connect/_proto/redpanda/runtime/v1alpha1/output_pb2_grpc.pyi
redpanda_connect/_proto/redpanda/runtime/v1alpha1/processor_pb2.py
redpanda_connect/_proto/redpanda/runtime/v1alpha1/processor_pb2.pyi
redpanda_connect/_proto/redpanda/runtime/v1alpha1/processor_pb2_grpc.py
redpanda_connect/_proto/redpanda/runtime/v1alpha1/processor_pb2_grpc.pyi
redpanda_connect-0.1.3.dist-info/METADATA
redpanda_connect-0.1.3.dist-info/WHEEL
redpanda_connect-0.1.3.dist-info/licenses/LICENSE
redpanda_connect-0.1.3.dist-info/RECORD
