Metadata-Version: 2.4
Name: redpanda-connect
Version: 0.1.3
Summary: A library for writing Redpanda Connect plugins in Python
Author-email: Tyler Rockwood <rockwood@redpanda.com>
License-Expression: Apache-2.0
License-File: LICENSE
Requires-Python: >=3.12
Requires-Dist: grpcio>=1.71.0
Requires-Dist: protobuf>=5.29.5
